task3/ram2ports.sv
module ram2ports #(
        parameter       ADDRESS_WIDTH = 9 ,
                        DATA_WIDTH = 8
)(
        input logic                             clk,
        input logic                             wr,
        input logic                             rd,
        input logic     [ADDRESS_WIDTH-1:0]     wr_addr,
        input logic     [ADDRESS_WIDTH-1:0]     rd_addr,
        input logic     [DATA_WIDTH-1:0]        mic_signal,
        output logic    [DATA_WIDTH-1:0]        delayed_signal
);

logic [DATA_WIDTH-1:0] ram_array [2**ADDRESS_WIDTH-1:0];    


always_ff @(posedge clk) begin
        if(wr == 1'b1)
                ram_array[wr_addr] <= mic_signal;
        if (rd == 1'b1)
                delayed_signal <= ram_array [rd_addr];
end;

endmodule

task2/counter.sv
module counter #(
    parameter WIDTH = 8
)(
    //interface signals
    input logic                 clk,        // clock
    input logic                 rst,        // reset
    input logic                 en,         // counter enable
    input logic     [WIDTH-1:0] incr, 
    output logic    [WIDTH-1:0] count       // count output

);

always_ff @ (posedge clk, posedge rst)
    if (rst)    count <= {WIDTH{1'b0}};
    else if (en)        count <= count + incr;

endmodule

task3/sigdelay.sv
module sigdelay #(
    parameter   A_WIDTH = 9,
                D_WIDTH = 8
)(
    // interface signals
    input logic                 clk,
    input logic                 rst,
    input logic                 en,
    input logic                 wr,
    input logic                 rd,
    input logic [D_WIDTH-1:0]   incr,
    input logic [D_WIDTH-1:0]   offset,
    input logic [D_WIDTH-1:0]   mic_signal,
    output logic [D_WIDTH-1:0]  delayed_signal

);

    logic [A_WIDTH-1:0]      address; 

counter addrCounter (
    .clk (clk),
    .rst (rst),
    .en (en),
    .incr (incr),
    .count (address)
);

ram2ports sineRom (
    .clk (clk),
    .wr (wr),
    .rd (rd),
    .wr_addr (address),
    .rd_addr (address-offset),
    .mic_signal (mic_signal),
    .delayed_signal (delayed_signal)
);

endmodule

task3/sigdelay.vcd
$version Generated by VerilatedVcd $end
$timescale 1ps $end

 $scope module TOP $end
  $var wire  1 # clk $end
  $var wire  8 + delayed_signal [7:0] $end
  $var wire  1 % en $end
  $var wire  8 ( incr [7:0] $end
  $var wire  8 * mic_signal [7:0] $end
  $var wire  8 ) offset [7:0] $end
  $var wire  1 ' rd $end
  $var wire  1 $ rst $end
  $var wire  1 & wr $end
  $scope module sigdelay $end
   $var wire 32 / A_WIDTH [31:0] $end
   $var wire 32 0 D_WIDTH [31:0] $end
   $var wire  9 , address [8:0] $end
   $var wire  1 # clk $end
   $var wire  8 + delayed_signal [7:0] $end
   $var wire  1 % en $end
   $var wire  8 ( incr [7:0] $end
   $var wire  8 * mic_signal [7:0] $end
   $var wire  8 ) offset [7:0] $end
   $var wire  1 ' rd $end
   $var wire  1 $ rst $end
   $var wire  1 & wr $end
   $scope module addrCounter $end
    $var wire 32 0 WIDTH [31:0] $end
    $var wire  1 # clk $end
    $var wire  8 - count [7:0] $end
    $var wire  1 % en $end
    $var wire  8 ( incr [7:0] $end
    $var wire  1 $ rst $end
   $upscope $end
   $scope module sineRom $end
    $var wire 32 / ADDRESS_WIDTH [31:0] $end
    $var wire 32 0 DATA_WIDTH [31:0] $end
    $var wire  1 # clk $end
    $var wire  8 + delayed_signal [7:0] $end
    $var wire  8 * mic_signal [7:0] $end
    $var wire  1 ' rd $end
    $var wire  9 . rd_addr [8:0] $end
    $var wire  1 & wr $end
    $var wire  9 , wr_addr [8:0] $end
   $upscope $end
  $upscope $end
 $upscope $end
$enddefinitions $end


#0
1#
0$
0%
1&
1'
b00000001 (
b01000000 )
b00000000 *
b00000000 +
b000000000 ,
b00000000 -
b111000000 .
b00000000000000000000000000001001 /
b00000000000000000000000000001000 0
#1
0#
#2
1#
b00100000 )
b01101000 *
b111100000 .
#3
0#
#4
1#
b01101101 *
#5
0#
#6
1#
b01101100 *
#7
0#
#8
1#
b01101001 *
#9
0#
#10
1#
#11
0#
#12
1#
b01101110 *
#13
0#
#14
1#
b01101010 *
#15
0#
#16
1#
b01101100 *
#17
0#
#18
1#
b01110000 *
#19
0#
#20
1#
#21
0#
#22
1#
b01101110 *
#23
0#
#24
1#
b01101100 *
#25
0#
#26
1#
b01101110 *
#27
0#
#28
1#
b01110001 *
#29
0#
#30
1#
b01100101 *
#31
0#
#32
1#
b01100111 *
#33
0#
#34
1#
b01101110 *
#35
0#
#36
1#
b01100100 *
#37
0#
#38
1#
b01100001 *
#39
0#
#40
1#
b01101011 *
#41
0#
#42
1#
b01101000 *
#43
0#
#44
1#
b01100100 *
#45
0#
#46
1#
b01100110 *
#47
0#
#48
1#
b01101111 *
#49
0#
#50
1#
b01100111 *
#51
0#
#52
1#
#53
0#
#54
1#
b01101111 *
#55
0#
#56
1#
b01101100 *
#57
0#
#58
1#
b01100100 *
#59
0#
#60
1#
b01101000 *
#61
0#
#62
1#
b01101110 *
#63
0#
#64
1#
b01100111 *
#65
0#
#66
1#
b01101000 *
#67
0#
#68
1#
b01101110 *
#69
0#
#70
1#
b01101000 *
#71
0#
#72
1#
#73
0#
#74
1#
b01101110 *
#75
0#
#76
1#
b01101111 *
#77
0#
#78
1#
b01101100 *
#79
0#
#80
1#
b01101010 *
#81
0#
#82
1#
b01101001 *
#83
0#
#84
1#
#85
0#
#86
1#
#87
0#
#88
1#
b01100111 *
#89
0#
#90
1#
b01100100 *
#91
0#
#92
1#
b01101000 *
#93
0#
#94
1#
b01100111 *
#95
0#
#96
1#
b01101010 *
#97
0#
#98
1#
#99
0#
#100
1#
b01101111 *
#101
0#
#102
1#
b01101011 *
#103
0#
#104
1#
b01101101 *
#105
0#
#106
1#
b01110001 *
#107
0#
#108
1#
b01110000 *
#109
0#
#110
1#
b01101010 *
#111
0#
#112
1#
b01101011 *
#113
0#
#114
1#
b01101100 *
#115
0#
#116
1#
b01101111 *
#117
0#
#118
1#
#119
0#
#120
1#
b01101110 *
#121
0#
#122
1#
b01101111 *
#123
0#
#124
1#
b01101100 *
#125
0#
#126
1#
b01101001 *
#127
0#
#128
1#
b01110011 *
#129
0#
#130
1#
b01110000 *
#131
0#
#132
1#
b01101111 *
#133
0#
#134
1#
b01110000 *
#135
0#
#136
1#
b01110010 *
#137
0#
#138
1#
b01101101 *
#139
0#
#140
1#
#141
0#
#142
1#
b01110000 *
#143
0#
#144
1#
b01101111 *
#145
0#
#146
1#
#147
0#
#148
1#
b01101011 *
#149
0#
#150
1#
b01101001 *
#151
0#
#152
1#
b01100111 *
#153
0#
#154
1#
b01100110 *
#155
0#
#156
1#
b01101101 *
#157
0#
#158
1#
b01101100 *
#159
0#
#160
1#
b01101101 *
#161
0#
#162
1#
b01100111 *
#163
0#
#164
1#
b01101100 *
#165
0#
#166
1#
#167
0#
#168
1#
b01101101 *
#169
0#
#170
1#
b01101011 *
#171
0#
#172
1#
b01101001 *
#173
0#
#174
1#
b01101010 *
#175
0#
#176
1#
b01101011 *
#177
0#
#178
1#
b01101110 *
#179
0#
#180
1#
b01101000 *
#181
0#
#182
1#
b01101101 *
#183
0#
#184
1#
b01101100 *
#185
0#
#186
1#
b01101010 *
#187
0#
#188
1#
b01101011 *
#189
0#
#190
1#
b01101000 *
#191
0#
#192
1#
b01101100 *
#193
0#
#194
1#
b01101010 *
#195
0#
#196
1#
#197
0#
#198
1#
b01101011 *
#199
0#
#200
1#
b01101001 *
#201
0#
#202
1#
b01101000 *
#203
0#
#204
1#
b01100110 *
#205
0#
#206
1#
#207
0#
#208
1#
b01100101 *
#209
0#
#210
1#
b01100110 *
#211
0#
#212
1#
b01101001 *
#213
0#
#214
1#
b01101000 *
#215
0#
#216
1#
#217
0#
#218
1#
b01101110 *
#219
0#
#220
1#
#221
0#
#222
1#
b01101101 *
#223
0#
#224
1#
#225
0#
#226
1#
b01110001 *
#227
0#
#228
1#
b01101011 *
#229
0#
#230
1#
b01101100 *
#231
0#
#232
1#
#233
0#
#234
1#
b01101000 *
#235
0#
#236
1#
b01101001 *
#237
0#
#238
1#
b01101010 *
#239
0#
#240
1#
b01101011 *
#241
0#
#242
1#
b01101010 *
#243
0#
#244
1#
b01101000 *
#245
0#
#246
1#
b01101011 *
#247
0#
#248
1#
b01101010 *
#249
0#
#250
1#
#251
0#
#252
1#
b01101101 *
#253
0#
#254
1#
#255
0#
#256
1#
#257
0#
#258
1#
b01101110 *
#259
0#
#260
1#
b01101111 *
#261
0#
#262
1#
b01101100 *
#263
0#
#264
1#
b01101110 *
#265
0#
#266
1#
#267
0#
#268
1#
b01101111 *
#269
0#
#270
1#
b01101101 *
#271
0#
#272
1#
b01110010 *
#273
0#
#274
1#
b01110011 *
#275
0#
#276
1#
b01101110 *
#277
0#
#278
1#
b01101101 *
#279
0#
#280
1#
b01110011 *
#281
0#
#282
1#
b01101111 *
#283
0#
#284
1#
#285
0#
#286
1#
b01101100 *
#287
0#
#288
1#
b01101101 *
#289
0#
#290
1#
#291
0#
#292
1#
#293
0#
#294
1#
b01101100 *
#295
0#
#296
1#
b01101011 *
#297
0#
#298
1#
b01101100 *
#299
0#
#300
1#
b01101010 *
#301
0#
#302
1#
#303
0#
#304
1#
b01110001 *
#305
0#
#306
1#
b01101110 *
#307
0#
#308
1#
#309
0#
#310
1#
b01110010 *
#311
0#
#312
1#
b01110000 *
#313
0#
#314
1#
b01101110 *
#315
0#
#316
1#
b01101111 *
#317
0#
#318
1#
b01101011 *
#319
0#
#320
1#
b01101010 *
#321
0#
#322
1#
#323
0#
#324
1#
#325
0#
#326
1#
#327
0#
#328
1#
b01100111 *
#329
0#
#330
1#
#331
0#
#332
1#
b01100011 *
#333
0#
#334
1#
b01100110 *
#335
0#
#336
1#
b01100101 *
#337
0#
#338
1#
b01100100 *
#339
0#
#340
1#
b01100010 *
#341
0#
#342
1#
b01100101 *
#343
0#
#344
1#
b01101011 *
#345
0#
#346
1#
b01100111 *
#347
0#
#348
1#
b01101010 *
#349
0#
#350
1#
b01101111 *
#351
0#
#352
1#
b01101100 *
#353
0#
#354
1#
b01101010 *
#355
0#
#356
1#
b01101110 *
#357
0#
#358
1#
b01101101 *
#359
0#
#360
1#
b01101011 *
#361
0#
#362
1#
b01101010 *
#363
0#
#364
1#
#365
0#
#366
1#
b01101000 *
#367
0#
#368
1#
#369
0#
#370
1#
b01100101 *
#371
0#
#372
1#
#373
0#
#374
1#
b01100111 *
#375
0#
#376
1#
b01100110 *
#377
0#
#378
1#
b01100011 *
#379
0#
#380
1#
#381
0#
#382
1#
b01100010 *
#383
0#
#384
1#
b01100001 *
#385
0#
#386
1#
b01100100 *
#387
0#
#388
1#
b01100010 *
#389
0#
#390
1#
b01101000 *
#391
0#
#392
1#
b01100101 *
#393
0#
#394
1#
b01100111 *
#395
0#
#396
1#
b01101011 *
#397
0#
#398
1#
#399
0#
#400
1#
b01101110 *
#401
0#
#402
1#
b01101100 *
#403
0#
#404
1#
b01101101 *
#405
0#
#406
1#
b01101010 *
#407
0#
#408
1#
b01101110 *
#409
0#
#410
1#
#411
0#
#412
1#
b01101101 *
#413
0#
#414
1#
#415
0#
#416
1#
#417
0#
#418
1#
b01101100 *
#419
0#
#420
1#
b01101011 *
#421
0#
#422
1#
b01101101 *
#423
0#
#424
1#
b01101110 *
#425
0#
#426
1#
b01101111 *
#427
0#
#428
1#
b01101101 *
#429
0#
#430
1#
b01101110 *
#431
0#
#432
1#
b01101100 *
#433
0#
#434
1#
b01101101 *
#435
0#
#436
1#
b01101000 *
#437
0#
#438
1#
b01101001 *
#439
0#
#440
1#
b01101101 *
#441
0#
#442
1#
b01101011 *
#443
0#
#444
1#
b01101001 *
#445
0#
#446
1#
b01101100 *
#447
0#
#448
1#
b01101110 *
#449
0#
#450
1#
#451
0#
#452
1#
b01101100 *
#453
0#
#454
1#
b01101101 *
#455
0#
#456
1#
b01101100 *
#457
0#
#458
1#
b01101010 *
#459
0#
#460
1#
#461
0#
#462
1#
b01101001 *
#463
0#
#464
1#
b01101110 *
#465
0#
#466
1#
b01101011 *
#467
0#
#468
1#
b01101100 *
#469
0#
#470
1#
b01110001 *
#471
0#
#472
1#
b01101110 *
#473
0#
#474
1#
#475
0#
#476
1#
b01101111 *
#477
0#
#478
1#
b01110010 *
#479
0#
#480
1#
b01101100 *
#481
0#
#482
1#
b01101110 *
#483
0#
#484
1#
b01101111 *
#485
0#
#486
1#
b01101011 *
#487
0#
#488
1#
b01101100 *
#489
0#
#490
1#
#491
0#
#492
1#
b01101110 *
#493
0#
#494
1#
b01101010 *
#495
0#
#496
1#
b01101111 *
#497
0#
#498
1#
b01101011 *
#499
0#
#500
1#
b01101010 *
#501
0#
#502
1#
#503
0#
#504
1#
b01101100 *
#505
0#
#506
1#
b01101110 *
#507
0#
#508
1#
b01101101 *
#509
0#
#510
1#
b01101110 *
#511
0#
#512
1#
b01101000 *
#513
0#
#514
1#
b01101011 *
#515
0#
#516
1#
b01101100 *
#517
0#
#518
1#
b01101011 *
#519
0#
#520
1#
b01101111 *
#521
0#
#522
1#
b01101001 *
#523
0#
#524
1#
b01101000 *
#525
0#
#526
1#
#527
0#
#528
1#
b01101001 *
#529
0#
#530
1#
#531
0#
#532
1#
b01100100 *
#533
0#
#534
1#
b01101001 *
#535
0#
#536
1#
b01101100 *
#537
0#
#538
1#
#539
0#
#540
1#
#541
0#
#542
1#
b01101011 *
#543
0#
#544
1#
#545
0#
#546
1#
b01101010 *
#547
0#
#548
1#
b01101001 *
#549
0#
#550
1#
b01101010 *
#551
0#
#552
1#
#553
0#
#554
1#
b01101001 *
#555
0#
#556
1#
b01101000 *
#557
0#
#558
1#
b01100110 *
#559
0#
#560
1#
b01100111 *
#561
0#
#562
1#
b01101001 *
#563
0#
#564
1#
b01101000 *
#565
0#
#566
1#
b01101011 *
#567
0#
#568
1#
b01101101 *
#569
0#
#570
1#
b01110000 *
#571
0#
#572
1#
b01101101 *
#573
0#
#574
1#
b01101110 *
#575
0#
#576
1#
#577
0#
#578
1#
b01110000 *
#579
0#
#580
1#
b01110001 *
#581
0#
#582
1#
b01101010 *
#583
0#
#584
1#
b01101000 *
#585
0#
#586
1#
b01101010 *
#587
0#
#588
1#
b01101000 *
#589
0#
#590
1#
b01100110 *
#591
0#
#592
1#
b01100100 *
#593
0#
#594
1#
b01101000 *
#595
0#
#596
1#
b01100111 *
#597
0#
#598
1#
b01101010 *
#599
0#
#600
1#
#601
0#
#602
1#
b01101011 *
#603
0#
#604
1#
b01101100 *
#605
0#
#606
1#
b01101110 *
#607
0#
#608
1#
b01110010 *
#609
0#
#610
1#
b01101110 *
#611
0#
#612
1#
b01110001 *
#613
0#
#614
1#
b01110010 *
#615
0#
#616
1#
b01110011 *
#617
0#
#618
1#
#619
0#
#620
1#
#621
0#
#622
1#
b01110100 *
#623
0#
#624
1#
b01110101 *
#625
0#
#626
1#
b01110010 *
#627
0#
#628
1#
#629
0#
#630
1#
b01110000 *
#631
0#
#632
1#
b01110011 *
#633
0#
#634
1#
b01110010 *
#635
0#
#636
1#
b01101111 *
#637
0#
#638
1#
b01110000 *
#639
0#
#640
1#
#641
0#
#642
1#
b01101110 *
#643
0#
#644
1#
b01101101 *
#645
0#
#646
1#
b01101000 *
#647
0#
#648
1#
b01101010 *
#649
0#
#650
1#
b01101000 *
#651
0#
#652
1#
b01100101 *
#653
0#
#654
1#
b01101001 *
#655
0#
#656
1#
b01100111 *
#657
0#
#658
1#
b01100110 *
#659
0#
#660
1#
b01100101 *
#661
0#
#662
1#
#663
0#
#664
1#
b01100111 *
#665
0#
#666
1#
#667
0#
#668
1#
b01101000 *
#669
0#
#670
1#
b01101010 *
#671
0#
#672
1#
b01101001 *
#673
0#
#674
1#
b01101101 *
#675
0#
#676
1#
b01101110 *
#677
0#
#678
1#
b01101111 *
#679
0#
#680
1#
b01110001 *
#681
0#
#682
1#
b01110010 *
#683
0#
#684
1#
b01110001 *
#685
0#
#686
1#
b01101111 *
#687
0#
#688
1#
b01110001 *
#689
0#
#690
1#
b01110110 *
#691
0#
#692
1#
b01110111 *
#693
0#
#694
1#
b01110011 *
#695
0#
#696
1#
b01110110 *
#697
0#
#698
1#
b01110100 *
#699
0#
#700
1#
b01110011 *
#701
0#
#702
1#
b01110001 *
#703
0#
#704
1#
b01101110 *
#705
0#
#706
1#
b01101101 *
#707
0#
#708
1#
b01101011 *
#709
0#
#710
1#
b01101010 *
#711
0#
#712
1#
b01101001 *
#713
0#
#714
1#
b01101000 *
#715
0#
#716
1#
#717
0#
#718
1#
b01100100 *
#719
0#
#720
1#
#721
0#
#722
1#
b01100011 *
#723
0#
#724
1#
b01100010 *
#725
0#
#726
1#
b01100101 *
#727
0#
#728
1#
b01100100 *
#729
0#
#730
1#
b01100011 *
#731
0#
#732
1#
b01100101 *
#733
0#
#734
1#
b01100110 *
#735
0#
#736
1#
b01100111 *
#737
0#
#738
1#
#739
0#
#740
1#
b01100110 *
#741
0#
#742
1#
b01101010 *
#743
0#
#744
1#
b01101110 *
#745
0#
#746
1#
b01101100 *
#747
0#
#748
1#
b01100111 *
#749
0#
#750
1#
b01101100 *
#751
0#
#752
1#
b01100111 *
#753
0#
#754
1#
b01101011 *
#755
0#
#756
1#
b01101101 *
#757
0#
#758
1#
#759
0#
#760
1#
b01101010 *
#761
0#
#762
1#
b01101101 *
#763
0#
#764
1#
b01101111 *
#765
0#
#766
1#
b01101100 *
#767
0#
#768
1#
b01101101 *
#769
0#
#770
1#
b01101100 *
#771
0#
#772
1#
b01110000 *
#773
0#
#774
1#
b01101101 *
#775
0#
#776
1#
b01101110 *
#777
0#
#778
1#
b01110000 *
#779
0#
#780
1#
b01101101 *
#781
0#
#782
1#
b01110000 *
#783
0#
#784
1#
#785
0#
#786
1#
b01110010 *
#787
0#
#788
1#
b01110000 *
#789
0#
#790
1#
b01110011 *
#791
0#
#792
1#
b01110000 *
#793
0#
#794
1#
b01101111 *
#795
0#
#796
1#
b01101100 *
#797
0#
#798
1#
b01101111 *
#799
0#
#800
1#
b01110000 *
#801
0#
#802
1#
b01101011 *
#803
0#
#804
1#
b01101010 *
#805
0#
#806
1#
#807
0#
#808
1#
b01101011 *
#809
0#
#810
1#
b01100111 *
#811
0#
#812
1#
#813
0#
#814
1#
#815
0#
#816
1#
b01101001 *
#817
0#
#818
1#
b01101010 *
#819
0#
#820
1#
b01101011 *
#821
0#
#822
1#
#823
0#
#824
1#
b01101001 *
#825
0#
#826
1#
#827
0#
#828
1#
#829
0#
#830
1#
#831
0#
#832
1#
b01101010 *
#833
0#
#834
1#
b01100110 *
#835
0#
#836
1#
b01101010 *
#837
0#
#838
1#
#839
0#
#840
1#
b01101100 *
#841
0#
#842
1#
b01101011 *
#843
0#
#844
1#
b01101101 *
#845
0#
#846
1#
#847
0#
#848
1#
b01101000 *
#849
0#
#850
1#
b01101001 *
#851
0#
#852
1#
b01101000 *
#853
0#
#854
1#
b01100101 *
#855
0#
#856
1#
b01100111 *
#857
0#
#858
1#
b01101011 *
#859
0#
#860
1#
b01101111 *
#861
0#
#862
1#
b01110000 *
#863
0#
#864
1#
b01110001 *
#865
0#
#866
1#
b01110000 *
#867
0#
#868
1#
b01110010 *
#869
0#
#870
1#
#871
0#
#872
1#
#873
0#
#874
1#
b01101111 *
#875
0#
#876
1#
b01101101 *
#877
0#
#878
1#
b01101100 *
#879
0#
#880
1#
#881
0#
#882
1#
#883
0#
#884
1#
#885
0#
#886
1#
b01101101 *
#887
0#
#888
1#
b01101000 *
#889
0#
#890
1#
#891
0#
#892
1#
b01100111 *
#893
0#
#894
1#
#895
0#
#896
1#
b01100110 *
#897
0#
#898
1#
b01101000 *
#899
0#
#900
1#
#901
0#
#902
1#
b01100100 *
#903
0#
#904
1#
b01101000 *
#905
0#
#906
1#
b01101010 *
#907
0#
#908
1#
#909
0#
#910
1#
b01101001 *
#911
0#
#912
1#
#913
0#
#914
1#
b01101010 *
#915
0#
#916
1#
b01100101 *
#917
0#
#918
1#
b01100110 *
#919
0#
#920
1#
b01100011 *
#921
0#
#922
1#
b01100000 *
#923
0#
#924
1#
b01100010 *
#925
0#
#926
1#
b01011100 *
#927
0#
#928
1#
#929
0#
#930
1#
b01011101 *
#931
0#
#932
1#
b01100001 *
#933
0#
#934
1#
b01011101 *
#935
0#
#936
1#
b01100010 *
#937
0#
#938
1#
b01101000 *
#939
0#
#940
1#
b01100100 *
#941
0#
#942
1#
b01100110 *
#943
0#
#944
1#
b01101000 *
#945
0#
#946
1#
b01101100 *
#947
0#
#948
1#
b01110000 *
#949
0#
#950
1#
#951
0#
#952
1#
b01110001 *
#953
0#
#954
1#
b01110000 *
#955
0#
#956
1#
b01110010 *
#957
0#
#958
1#
b01110100 *
#959
0#
#960
1#
b01110101 *
#961
0#
#962
1#
b01110000 *
#963
0#
#964
1#
b01110011 *
#965
0#
#966
1#
#967
0#
#968
1#
b01110001 *
#969
0#
#970
1#
b01101111 *
#971
0#
#972
1#
b01101101 *
#973
0#
#974
1#
b01101110 *
#975
0#
#976
1#
b01110000 *
#977
0#
#978
1#
b01101011 *
#979
0#
#980
1#
b01101101 *
#981
0#
#982
1#
#983
0#
#984
1#
b01101100 *
#985
0#
#986
1#
b01101011 *
#987
0#
#988
1#
b01101001 *
#989
0#
#990
1#
b01101100 *
#991
0#
#992
1#
b01101111 *
#993
0#
#994
1#
b01101101 *
#995
0#
#996
1#
b01110000 *
#997
0#
#998
1#
b01101111 *
#999
0#
#1000
1#
#1001
0#
#1002
1#
#1003
0#
#1004
1#
b01110001 *
#1005
0#
#1006
1#
b01101110 *
#1007
0#
#1008
1#
#1009
0#
#1010
1#
#1011
0#
#1012
1#
b01101101 *
#1013
0#
#1014
1#
b01110011 *
#1015
0#
#1016
1#
b01110010 *
#1017
0#
#1018
1#
#1019
0#
#1020
1#
b01110011 *
#1021
0#
#1022
1#
b01110000 *
#1023
0#
#1024
1#
b01110001 *
#1025
0#
#1026
1#
b01100010 *
#1027
0#
#1028
1#
b01100100 *
#1029
0#
#1030
1#
#1031
0#
#1032
1#
b01100101 *
#1033
0#
#1034
1#
#1035
0#
#1036
1#
b01100111 *
#1037
0#
#1038
1#
b01101000 *
#1039
0#
#1040
1#
#1041
0#
#1042
1#
b01101011 *
#1043
0#
#1044
1#
b01101111 *
#1045
0#
#1046
1#
b01101101 *
#1047
0#
#1048
1#
b01101110 *
#1049
0#
#1050
1#
b01101111 *
#1051
0#
#1052
1#
#1053
0#
#1054
1#
b01101110 *
#1055
0#
#1056
1#
b01101101 *
#1057
0#
#1058
1#
b01101010 *
#1059
0#
#1060
1#
#1061
0#
#1062
1#
#1063
0#
#1064
1#
#1065
0#
#1066
1#
#1067
0#
#1068
1#
#1069
0#
#1070
1#
b01101101 *
#1071
0#
#1072
1#
b01101110 *
#1073
0#
#1074
1#
b01101100 *
#1075
0#
#1076
1#
b01101101 *
#1077
0#
#1078
1#
b01101110 *
#1079
0#
#1080
1#
b01110001 *
#1081
0#
#1082
1#
#1083
0#
#1084
1#
b01110110 *
#1085
0#
#1086
1#
b01110111 *
#1087
0#
#1088
1#
#1089
0#
#1090
1#
b01110100 *
#1091
0#
#1092
1#
b01110010 *
#1093
0#
#1094
1#
b01101111 *
#1095
0#
#1096
1#
b01101110 *
#1097
0#
#1098
1#
b01101010 *
#1099
0#
#1100
1#
b01100110 *
#1101
0#
#1102
1#
#1103
0#
#1104
1#
b01100111 *
#1105
0#
#1106
1#
b01100100 *
#1107
0#
#1108
1#
b01100010 *
#1109
0#
#1110
1#
#1111
0#
#1112
1#
b01100000 *
#1113
0#
#1114
1#
b01100001 *
#1115
0#
#1116
1#
b01100011 *
#1117
0#
#1118
1#
#1119
0#
#1120
1#
b01101000 *
#1121
0#
#1122
1#
b01101100 *
#1123
0#
#1124
1#
b01110000 *
#1125
0#
#1126
1#
#1127
0#
#1128
1#
b01110011 *
#1129
0#
#1130
1#
b01110010 *
#1131
0#
#1132
1#
b01110011 *
#1133
0#
#1134
1#
b01101110 *
#1135
0#
#1136
1#
b01101111 *
#1137
0#
#1138
1#
b01110010 *
#1139
0#
#1140
1#
b01101101 *
#1141
0#
#1142
1#
#1143
0#
#1144
1#
b01101100 *
#1145
0#
#1146
1#
b01100101 *
#1147
0#
#1148
1#
b01100010 *
#1149
0#
#1150
1#
b01100000 *
#1151
0#
#1152
1#
b01011101 *
#1153
0#
#1154
1#
b01011100 *
#1155
0#
#1156
1#
b01011101 *
#1157
0#
#1158
1#
b01100000 *
#1159
0#
#1160
1#
b01100100 *
#1161
0#
#1162
1#
b01100101 *
#1163
0#
#1164
1#
b01101000 *
#1165
0#
#1166
1#
b01101001 *
#1167
0#
#1168
1#
b01101011 *
#1169
0#
#1170
1#
b01101110 *
#1171
0#
#1172
1#
b01110100 *
#1173
0#
#1174
1#
b01110101 *
#1175
0#
#1176
1#
b01111001 *
#1177
0#
#1178
1#
b01111000 *
#1179
0#
#1180
1#
b01111100 *
#1181
0#
#1182
1#
b01111000 *
#1183
0#
#1184
1#
b01111001 *
#1185
0#
#1186
1#
b01110101 *
#1187
0#
#1188
1#
b01110000 *
#1189
0#
#1190
1#
#1191
0#
#1192
1#
b01101010 *
#1193
0#
#1194
1#
b01101011 *
#1195
0#
#1196
1#
b01101001 *
#1197
0#
#1198
1#
b01100110 *
#1199
0#
#1200
1#
b01101010 *
#1201
0#
#1202
1#
b01101001 *
#1203
0#
#1204
1#
b01101100 *
#1205
0#
#1206
1#
b01101111 *
#1207
0#
#1208
1#
b01110010 *
#1209
0#
#1210
1#
b01110110 *
#1211
0#
#1212
1#
b01111011 *
#1213
0#
#1214
1#
#1215
0#
#1216
1#
b01111001 *
#1217
0#
#1218
1#
b01111010 *
#1219
0#
#1220
1#
b01110110 *
#1221
0#
#1222
1#
b01110100 *
#1223
0#
#1224
1#
b01101110 *
#1225
0#
#1226
1#
b01101111 *
#1227
0#
#1228
1#
#1229
0#
#1230
1#
b01101011 *
#1231
0#
#1232
1#
b01100111 *
#1233
0#
#1234
1#
#1235
0#
#1236
1#
b01100011 *
#1237
0#
#1238
1#
b01100010 *
#1239
0#
#1240
1#
b01011111 *
#1241
0#
#1242
1#
b01100001 *
#1243
0#
#1244
1#
#1245
0#
#1246
1#
b01100101 *
#1247
0#
#1248
1#
b01100111 *
#1249
0#
#1250
1#
b01101010 *
#1251
0#
#1252
1#
b01101101 *
#1253
0#
#1254
1#
b01110001 *
#1255
0#
#1256
1#
b01110100 *
#1257
0#
#1258
1#
b01110101 *
#1259
0#
#1260
1#
b01110100 *
#1261
0#
#1262
1#
b01110010 *
#1263
0#
#1264
1#
b01110011 *
#1265
0#
#1266
1#
#1267
0#
#1268
1#
b01101111 *
#1269
0#
#1270
1#
b01101011 *
#1271
0#
#1272
1#
b01100111 *
#1273
0#
#1274
1#
b01101011 *
#1275
0#
#1276
1#
b01100011 *
#1277
0#
#1278
1#
#1279
0#
#1280
1#
#1281
0#
#1282
1#
b01100010 *
#1283
0#
#1284
1#
b01100001 *
#1285
0#
#1286
1#
#1287
0#
#1288
1#
b01100101 *
#1289
0#
#1290
1#
b01100011 *
#1291
0#
#1292
1#
b01100101 *
#1293
0#
#1294
1#
b01100111 *
#1295
0#
#1296
1#
b01101011 *
#1297
0#
#1298
1#
b01101110 *
#1299
0#
#1300
1#
b01101111 *
#1301
0#
#1302
1#
b01110111 *
#1303
0#
#1304
1#
b01110011 *
#1305
0#
#1306
1#
b01110101 *
#1307
0#
#1308
1#
#1309
0#
#1310
1#
b01110011 *
#1311
0#
#1312
1#
b01101110 *
#1313
0#
#1314
1#
b01101011 *
#1315
0#
#1316
1#
b01101001 *
#1317
0#
#1318
1#
b01101010 *
#1319
0#
#1320
1#
b01101000 *
#1321
0#
#1322
1#
b01100100 *
#1323
0#
#1324
1#
b01100010 *
#1325
0#
#1326
1#
b01100001 *
#1327
0#
#1328
1#
b01100011 *
#1329
0#
#1330
1#
b01100010 *
#1331
0#
#1332
1#
b01100110 *
#1333
0#
#1334
1#
b01100100 *
#1335
0#
#1336
1#
b01101000 *
#1337
0#
#1338
1#
b01101010 *
#1339
0#
#1340
1#
b01110011 *
#1341
0#
#1342
1#
b01101110 *
#1343
0#
#1344
1#
b01110100 *
#1345
0#
#1346
1#
b00100001 )
b01110011 *
b111011111 .
#1347
0#
#1348
1#
b01110111 *
#1349
0#
#1350
1#
b00100010 )
b01111001 *
b111011110 .
#1351
0#
#1352
1#
b01110111 *
#1353
0#
#1354
1#
b01110101 *
#1355
0#
#1356
1#
b01111001 *
#1357
0#
#1358
1#
b01110011 *
#1359
0#
#1360
1#
#1361
0#
#1362
1#
b01101101 *
#1363
0#
#1364
1#
b01101100 *
#1365
0#
#1366
1#
b00100001 )
b01101110 *
b111011111 .
#1367
0#
#1368
1#
b01101001 *
#1369
0#
#1370
1#
b00100000 )
b01101010 *
b111100000 .
#1371
0#
#1372
1#
b00011111 )
b01101011 *
b111100001 .
#1373
0#
#1374
1#
b00011110 )
b111100010 .
#1375
0#
#1376
1#
b01101101 *
#1377
0#
#1378
1#
b01101110 *
#1379
0#
#1380
1#
b01110010 *
#1381
0#
#1382
1#
b01101110 *
#1383
0#
#1384
1#
b01101111 *
#1385
0#
#1386
1#
b01110001 *
#1387
0#
#1388
1#
#1389
0#
#1390
1#
#1391
0#
#1392
1#
#1393
0#
#1394
1#
b01110100 *
#1395
0#
#1396
1#
b01110001 *
#1397
0#
#1398
1#
b01101100 *
#1399
0#
#1400
1#
b01101010 *
#1401
0#
#1402
1#
b01101110 *
#1403
0#
#1404
1#
b01100100 *
#1405
0#
#1406
1#
b01100000 *
#1407
0#
#1408
1#
b01100001 *
#1409
0#
#1410
1#
b01100011 *
#1411
0#
#1412
1#
b01011101 *
#1413
0#
#1414
1#
b01100010 *
#1415
0#
#1416
1#
#1417
0#
#1418
1#
b00011101 )
b01100001 *
b111100011 .
#1419
0#
#1420
1#
b01100011 *
#1421
0#
